psyserver/__init__.py
psyserver/__main__.py
psyserver/db.py
psyserver/init.py
psyserver/main.py
psyserver/run.py
psyserver/settings.py
psyserver/example/favicon.ico
psyserver/example/filebrowser.toml
psyserver/example/log_config.toml
psyserver/example/psyserver.service
psyserver/example/psyserver.toml
psyserver/example/data/studies/exp_cute/accessories.js
psyserver/example/data/studies/exp_cute/image.html
psyserver/example/data/studies/exp_cute/index.html
psyserver/example/data/studies/exp_cute/main_script.js
psyserver/example/data/studies/exp_cute/style.css
psyserver/example/data/studies/exp_cute/tone.mp3
psyserver/example/data/studies/exp_cute/images/goat_1.jpg
psyserver/example/data/studies/exp_cute/images/goat_2.jpg
psyserver/example/data/studies/exp_cute/images/goat_3.jpg
psyserver/example/data/studies/exp_cute/images/sheep_1.jpg
psyserver/example/data/studies/exp_cute/images/sheep_2.jpg
psyserver/example/data/studies/exp_cute/images/sheep_3.jpg
psyserver/example/data/studydata/exp_cute/.gitkeep
psyserver-0.5.1.dist-info/entry_points.txt
psyserver-0.5.1.dist-info/LICENSE
psyserver-0.5.1.dist-info/WHEEL
psyserver-0.5.1.dist-info/METADATA
psyserver-0.5.1.dist-info/RECORD
