Metadata-Version: 2.1
Name: psyserver
Version: 0.5.1
Summary: A server to host your online studies on.
Keywords: experiments,studies,behavioral,online,server
Author-email: Gabriel Kressin Palacios <gabriel.kressin@homtail.de>
Requires-Python: >=3.11,<3.12
Requires-Dist: fastapi[all]>=0.104.0,<0.105.0
Requires-Dist: uvicorn[standard]>=0.23.0,<0.24.0
Requires-Dist: pytest ; extra == "dev"
Requires-Dist: httpx ; extra == "dev"
Requires-Dist: coverage ; extra == "dev"
Requires-Dist: flit ; extra == "dev"
Project-URL: Home, https://github.com/GabrielKP/psyserver
Provides-Extra: dev
